dateparse/__init__.py
dateparse/dateparser.py
dateparse/parsefunctions.py
dateparse/parseutil.py
dateparse/regex_utils.py
dateparse-1.4.0.dist-info/LICENSE.rst
dateparse-1.4.0.dist-info/METADATA
dateparse-1.4.0.dist-info/WHEEL
dateparse-1.4.0.dist-info/RECORD
