Metadata-Version: 2.1
Name: dateparse
Version: 1.4.0
Summary: A pure Python library for parsing natural language time expressions, with minimal dependencies
License: Unlicense
Author: keagud
Author-email: keagud@protonmail.com
Requires-Python: >=3.10,<4.0
Classifier: License :: Other/Proprietary License
Classifier: Programming Language :: Python :: 3
Classifier: Programming Language :: Python :: 3.10
Classifier: Programming Language :: Python :: 3.11
Requires-Dist: datetime (>=4.9,<5.0)
